setup.py
swarm_scheduler_api/__init__.py
swarm_scheduler_api/server.py
swarm_scheduler_api.egg-info/PKG-INFO
swarm_scheduler_api.egg-info/SOURCES.txt
swarm_scheduler_api.egg-info/dependency_links.txt
swarm_scheduler_api.egg-info/entry_points.txt
swarm_scheduler_api.egg-info/not-zip-safe
swarm_scheduler_api.egg-info/requires.txt
swarm_scheduler_api.egg-info/top_level.txt