Metadata-Version: 1.0
Name: swarm-scheduler-api
Version: 0.1.0
Summary: Swarm scheduler API example
Home-page: UNKNOWN
Author: Francis Bouvier 
Author-email: francis.bouvier@gmail.com
License: New BSD License
Platform: Any
